README.txt
setup.py
collective/__init__.py
collective.flowplayercaptions.egg-info/PKG-INFO
collective.flowplayercaptions.egg-info/SOURCES.txt
collective.flowplayercaptions.egg-info/dependency_links.txt
collective.flowplayercaptions.egg-info/entry_points.txt
collective.flowplayercaptions.egg-info/namespace_packages.txt
collective.flowplayercaptions.egg-info/not-zip-safe
collective.flowplayercaptions.egg-info/paster_plugins.txt
collective.flowplayercaptions.egg-info/requires.txt
collective.flowplayercaptions.egg-info/top_level.txt
collective/flowplayercaptions/__init__.py
collective/flowplayercaptions/configure.zcml
collective/flowplayercaptions/events.py
collective/flowplayercaptions/exportimport.py
collective/flowplayercaptions/extender.py
collective/flowplayercaptions/i18n.sh
collective/flowplayercaptions/interfaces.py
collective/flowplayercaptions/tests.py
collective/flowplayercaptions/Extensions/install.py
collective/flowplayercaptions/browser/__init__.py
collective/flowplayercaptions/browser/configure.zcml
collective/flowplayercaptions/browser/flowplayer.captions.js
collective/flowplayercaptions/browser/video_viewlet.pt
collective/flowplayercaptions/browser/viewlets.py
collective/flowplayercaptions/browser/swf/LICENSE.txt
collective/flowplayercaptions/browser/swf/flowplayer.captions-3.2.2.swf
collective/flowplayercaptions/browser/swf/flowplayer.content-3.2.0.swf
collective/flowplayercaptions/locales/collective.flowplayercaptions.pot
collective/flowplayercaptions/locales/it/LC_MESSAGES/collective.flowplayercaptions.po
collective/flowplayercaptions/profiles/default/browserlayer.xml
collective/flowplayercaptions/profiles/default/collective.flowplayercaptions.txt
collective/flowplayercaptions/profiles/default/jsregistry.xml
collective/flowplayercaptions/profiles/default/metadata.xml
collective/flowplayercaptions/profiles/uninstall/jsregistry.xml
docs/HISTORY.txt
docs/INSTALL.txt
docs/LICENSE.GPL
docs/LICENSE.txt