Metadata-Version: 1.0
Name: collective.flowplayercaptions
Version: 0.1.0
Summary: Plone support for captioning video contents that use collective.flowplayer
Home-page: http://plone.org/products/collective.flowplayercaptions
Author: keul
Author-email: luca@keul.it
License: GPL
Keywords: flowplayer captions plone subtitles video
Platform: UNKNOWN
Classifier: Framework :: Plone
Classifier: Programming Language :: Python
Classifier: Development Status :: 4 - Beta
